tbl/__init__.py
tbl-0.1.dist-info/METADATA
tbl-0.1.dist-info/RECORD
tbl-0.1.dist-info/WHEEL
tbl-0.1.dist-info/top_level.txt
